revfyawo/mongo/__init__.py
revfyawo/mongo/document.py
revfyawo.mongo-0.0.6.dist-info/METADATA
revfyawo.mongo-0.0.6.dist-info/RECORD
revfyawo.mongo-0.0.6.dist-info/WHEEL
revfyawo.mongo-0.0.6.dist-info/top_level.txt
